top/topsis.py
Rank_Predictor_101883054-1.0.2.dist-info/LICENSE.txt
Rank_Predictor_101883054-1.0.2.dist-info/METADATA
Rank_Predictor_101883054-1.0.2.dist-info/WHEEL
Rank_Predictor_101883054-1.0.2.dist-info/entry_points.txt
Rank_Predictor_101883054-1.0.2.dist-info/top_level.txt
Rank_Predictor_101883054-1.0.2.dist-info/RECORD
