Metadata-Version: 2.1
Name: Rank-Predictor-101883054
Version: 1.0.2
Summary: A python package to predict the rank of a MCDMP using topsis
Home-page: UNKNOWN
Author: Mehak Garg
License: MIT
Platform: UNKNOWN
Classifier: License :: OSI Approved :: MIT License
Classifier: Programming Language :: Python :: 3
Classifier: Programming Language :: Python :: 3.7
Requires-Dist: pandas
Requires-Dist: numpy
